paaws/__init__.py
paaws/__main__.py
paaws/app.py
paaws/docs.py
paaws/utils.py
paaws/cli/__init__.py
paaws/cli/builds.py
paaws/cli/config.py
paaws/cli/db.py
paaws/cli/deployments.py
paaws/cli/logs.py
paaws/cli/ps.py
paaws/cli/shell.py
paaws-0.1.dist-info/entry_points.txt
paaws-0.1.dist-info/LICENSE
paaws-0.1.dist-info/WHEEL
paaws-0.1.dist-info/METADATA
paaws-0.1.dist-info/RECORD
