Metadata-Version: 2.1
Name: paaws
Version: 0.1
Summary: Deploy control for ECS
Home-page: https://github.com/lincolnloop/paaws
License: License :: OSI Approved :: MIT License
Author: Peter Baumgartner
Author-email: pete@lincolnloop.com
Requires-Python: >=3.6
Requires-Dist: awscli
Requires-Dist: awslogs
Requires-Dist: blessed
Requires-Dist: boto3
Requires-Dist: click
Requires-Dist: halo
Requires-Dist: timeago
Requires-Dist: shiv ; extra == "dev"
Provides-Extra: dev
